BMPxlsx
