Metadata-Version: 2.1
Name: BMPxlsx
Version: 0.0.3
Summary: The library takes a dictionary of form {Sheet: {Cell: Value}} and updates the specified Excel file accordingly.
Home-page: https://github.com/TheAcademyofNaturalSciences/BMPxlsx
Author: Mike Campagna
Author-email: msc94@drexel.edu
License: MIT
Download-URL: https://github.com/TheAcademyofNaturalSciences/BMPxlsx/archive/v_003.tar.gz
Keywords: Excel,Write,XLSX,BMP
Platform: UNKNOWN
Classifier: Development Status :: 3 - Alpha
Classifier: Intended Audience :: Developers
Classifier: Topic :: Software Development :: Build Tools
Classifier: License :: OSI Approved :: MIT License
Classifier: Programming Language :: Python :: 2.7
